<?xml version="1.0" encoding="utf-8"?>
<regions>
  <region>
    <title>Greater Bangkok</title>
    <provinces>
      <province>>Bangkok</province>
      <province>>Samut Prakan</province>
      <province>>Nonthaburi</province>
      <province>>Pathum Thani</province>
    </provinces>
  </region>
  <region>
    <title>Central</title>
    <provinces>
      <province>>Ang Thong</province>
      <province>>Ayutthaya</province>
      <province>>Chainat</province>
      <province>>Kamphaeng Phet</province>
      <province>>Lopburi</province>
      <province>>Nakhon Nayok</province>
      <province>>Nakhon Pathom</province>
      <province>>Nakhon Sawan</province>
      <province>>Phetchabun</province>
      <province>>Phichit</province>
      <province>>Phitsanulok</province>
      <province>>Samut Sakhon</province>
      <province>>Samut Songkhram</province>
      <province>>Saraburi</province>
      <province>>Sing Buri</province>
      <province>>Sukhothai</province>
      <province>>Suphan Buri</province>
      <province>>Uthai Thani</province>
    </provinces>
  </region>
  <region>
    <title>East</title>
    <provinces>
      <province>>Chachoengsao</province>
      <province>>Chanthaburi</province>
      <province>>Chonburi</province>
      <province>>Prachin Buri</province>
      <province>>Rayong</province>
      <province>>Sa Kaeo</province>
      <province>>Trat</province>
    </provinces>
  </region>
  <region>
    <title>North</title>
    <provinces>
      <province>>Chiang Mai</province>
      <province>>Chiang Rai</province>
      <province>>Lampang</province>
      <province>>Lamphun</province>
      <province>>Mae Hong Son</province>
      <province>>Nan</province>
      <province>>Phayao</province>
      <province>>Phrae</province>
      <province>>Uttaradit</province>
    </provinces>
  </region>
  <region>
    <title>Northeast</title>
    <provinces>
      <province>>Amnat Charoen</province>
      <province>>Bueng Kan</province>
      <province>>Buriram</province>
      <province>>Chaiyaphum</province>
      <province>>Kalasin</province>
      <province>>Khon Kaen</province>
      <province>>Loei</province>
      <province>>Maha Sarakham</province>
      <province>>Mukdahan</province>
      <province>>Mukdahan</province>
      <province>>Nakhon Phanom</province>
      <province>>Nakhon Ratchasima</province>
      <province>>Nong Bua Lamphu</province>
      <province>>Nong Khai</province>
      <province>>Roi Et</province>
      <province>>Sakon Nakhon</province>
      <province>>Sisaket</province>
      <province>>Surin</province>
      <province>>Ubon Ratchathani</province>
      <province>>Udon Thani</province>
      <province>>Yasothon</province>
    </provinces>
  </region>
  <region>
    <title>South</title>
    <provinces>
      <province>>Chumphon</province>
      <province>>Krabi</province>
      <province>>Nakhon Si Thammarat</province>
      <province>>Narathiwat</province>
      <province>>Pattani</province>
      <province>>Phang Nga</province>
      <province>>Phatthalung</province>
      <province>>Phuket</province>
      <province>>Ranong</province>
      <province>>Satun</province>
      <province>>Songkhla</province>
      <province>>Surat Thani</province>
      <province>>Trang</province>
      <province>>Yala</province>
    </provinces>
  </region>
  <region>
    <title>West</title>
    <provinces>
      <province>>Kanchanaburi</province>
      <province>>Phetchaburi</province>
      <province>>Prachuap Khiri Khan</province>
      <province>>Ratchaburi</province>
      <province>>Tak</province>
    </provinces>
  </region>
</regions>
